discord_autoupdate/__init__.py
discord_autoupdate/main.py
discord_autoupdate-1.2.0.dist-info/METADATA
discord_autoupdate-1.2.0.dist-info/WHEEL
discord_autoupdate-1.2.0.dist-info/entry_points.txt
discord_autoupdate-1.2.0.dist-info/top_level.txt
discord_autoupdate-1.2.0.dist-info/RECORD
