Metadata-Version: 2.4
Name: discord-autoupdate
Version: 1.2.0
Summary: Automatically update and run Discord on Debian-based systems.
Author-email: "@readwithai" <talwrii@gmal.com>
Classifier: Programming Language :: Python :: 3
Classifier: License :: OSI Approved :: MIT License
Classifier: Operating System :: POSIX :: Linux
Requires-Python: >=3.8
Requires-Dist: requests
